pengxin_gtech_mcp_demo/__init__.py
pengxin_gtech_mcp_demo-0.1.0.dist-info/WHEEL
pengxin_gtech_mcp_demo-0.1.0.dist-info/entry_points.txt
pengxin_gtech_mcp_demo-0.1.0.dist-info/METADATA
pengxin_gtech_mcp_demo-0.1.0.dist-info/RECORD
