Metadata-Version: 2.3
Name: pengxin-gtech-mcp-demo
Version: 0.1.0
Summary: Add your description here
Requires-Dist: mcp[cli]>=1.12.3
Requires-Python: >=3.13
